pyoptquest/__init__.py
pyoptquest/extest.py
pyoptquest/optquest.jar
pyoptquest/pyoptquest.py
pyoptquest/weights.py
pyoptquest/examples/example_frontier.py
pyoptquest/examples/example_parallel.py
pyoptquest/examples/example_replication.py
pyoptquest/examples/example_replication_with_confidence.py
pyoptquest/examples/example_simple.py
pyoptquest/examples/example_solver.py
pyoptquest/examples/hello.py
pyoptquest/examples/oqo_example_all_variables.py
pyoptquest/examples/oqo_example_cell_tower_location.py
pyoptquest/examples/oqo_example_cell_tower_polygon_location.py
pyoptquest/examples/oqo_example_constraint.py
pyoptquest/examples/oqo_example_constraint_evaluator.py
pyoptquest/examples/oqo_example_frontier.py
pyoptquest/examples/oqo_example_gfo_convex.py
pyoptquest/examples/oqo_example_gfo_non_convex.py
pyoptquest/examples/oqo_example_non_linear_constraint.py
pyoptquest/examples/oqo_example_objective_evaluator.py
pyoptquest/examples/oqo_example_parabola.py
pyoptquest/examples/oqo_example_parallel_evaluations.py
pyoptquest/examples/oqo_example_permutation.py
pyoptquest/examples/oqo_example_radio_antenna.py
pyoptquest/examples/oqo_example_replications.py
pyoptquest/examples/oqo_example_replications_with_confidence.py
pyoptquest/examples/oqo_example_simulation.py
pyoptquest/examples/oqo_example_status_monitor.py
pyoptquest/examples/oqo_example_suggested_runs.py
pyoptquest/examples/oqo_example_user_stop.py
pyoptquest/examples/run-all-examples.bat
pyoptquest/examples/setup.xml
pyoptquest/examples/solutions.csv
pyoptquest-9.1.1.4.dist-info/METADATA
pyoptquest-9.1.1.4.dist-info/WHEEL
pyoptquest-9.1.1.4.dist-info/RECORD
