Metadata-Version: 2.1
Name: pyoptquest
Version: 9.1.1.4
Summary: A python wrapper around the OptQuest library; see more at https://www.opttek.com/products/optquest/
Project-URL: Homepage, https://www.opttek.com/
Author-email: OptTek <python@opttek.com>
Classifier: License :: OSI Approved :: Apache Software License
Classifier: Operating System :: OS Independent
Classifier: Programming Language :: Python :: 3
Requires-Python: >=3.7
Requires-Dist: pandas
Requires-Dist: pyjnius>=1.4.1
Provides-Extra: examples
Requires-Dist: matplotlib; extra == 'examples'
Requires-Dist: shapely; extra == 'examples'
